MauvaiseLangue/__init__.py
MauvaiseLangue/scraper.py
MauvaiseLangue-1.0.8.dist-info/METADATA
MauvaiseLangue-1.0.8.dist-info/WHEEL
MauvaiseLangue-1.0.8.dist-info/top_level.txt
MauvaiseLangue-1.0.8.dist-info/RECORD
